fdtd/__init__.py
fdtd/backend.py
fdtd/boundaries.py
fdtd/constants.py
fdtd/conversions.py
fdtd/detectors.py
fdtd/fourier.py
fdtd/grid.py
fdtd/objects.py
fdtd/sources.py
fdtd/typing_.py
fdtd/visualization.py
fdtd/waveforms.py
fdtd-0.3.5.dist-info/LICENSE
fdtd-0.3.5.dist-info/METADATA
fdtd-0.3.5.dist-info/WHEEL
fdtd-0.3.5.dist-info/top_level.txt
fdtd-0.3.5.dist-info/RECORD
